{
  "users": [
    {
      "name": "Beth Lowe",
      "id": 16
    },
    {
      "name": "Shawn Dooley",
      "id": 18
    },
    {
      "name": "Mr. Lloyd Upton",
      "id": 19
    },
    {
      "name": "Thelma Mraz Sr.",
      "id": 20
    }
  ],
  "albums": [
    {
      "userId": 18,
      "title": "Oriental Frozen Shirt",
      "id": 26
    },
    {
      "userId": 18,
      "title": "Bespoke Cotton Fish",
      "id": 27
    },
    {
      "userId": 16,
      "title": "Generic Fresh Soap",
      "id": 28
    },
    {
      "userId": 16,
      "title": "Luxurious Granite Bacon",
      "id": 29
    }
  ],
  "photos": [
    {
      "albumId": 28,
      "url": "https://loremflickr.com/150/150/abstract?lock=55982",
      "id": 1
    },
    {
      "albumId": 28,
      "url": "https://loremflickr.com/150/150/abstract?lock=26807",
      "id": 2
    }
  ]
}